openttdlab.py
openttdlab-0.0.75.dist-info/METADATA
openttdlab-0.0.75.dist-info/WHEEL
openttdlab-0.0.75.dist-info/licenses/LICENSE
openttdlab-0.0.75.dist-info/RECORD
