Metadata-Version: 2.4
Name: OpenTTDLab
Version: 0.0.75
Summary: Python framework for running reproducible experiments using OpenTTD
Project-URL: Source, https://github.com/michalc/OpenTTDLab
Author-email: Michal Charemza <michal@charemza.name>, Patric Stout <truebrain@openttd.org>
License-File: LICENSE
Classifier: License :: OSI Approved :: GNU General Public License v2 (GPLv2)
Classifier: Operating System :: OS Independent
Classifier: Programming Language :: Python :: 3
Requires-Python: >=3.8.0
Requires-Dist: dill>=0.3.8
Requires-Dist: httpx>=0.26.0
Requires-Dist: platformdirs>=4.1.0
Requires-Dist: pyyaml>=6.0.1
Requires-Dist: rich>=13.7.1
Provides-Extra: ci
Requires-Dist: coverage==7.4.0; extra == 'ci'
Requires-Dist: dill==0.3.8; extra == 'ci'
Requires-Dist: httpx==0.26.0; extra == 'ci'
Requires-Dist: platformdirs==4.1.0; extra == 'ci'
Requires-Dist: pytest-cov==4.1.0; extra == 'ci'
Requires-Dist: pytest==7.4.4; extra == 'ci'
Requires-Dist: pyyaml==6.0.1; extra == 'ci'
Requires-Dist: rich==13.7.1; extra == 'ci'
Provides-Extra: dev
Requires-Dist: coverage>=7.4.0; extra == 'dev'
Requires-Dist: pytest-cov>=4.1.0; extra == 'dev'
Requires-Dist: pytest>=7.4.4; extra == 'dev'
